streamlit_session_browser_storage/__init__.py
streamlit_session_browser_storage/example.py
streamlit_session_browser_storage/frontend/build/asset-manifest.json
streamlit_session_browser_storage/frontend/build/bootstrap.min.css
streamlit_session_browser_storage/frontend/build/bootstrap.min.css.map
streamlit_session_browser_storage/frontend/build/index.html
streamlit_session_browser_storage/frontend/build/static/js/main.afb225c6.js
streamlit_session_browser_storage/frontend/build/static/js/main.afb225c6.js.LICENSE.txt
streamlit_session_browser_storage/frontend/build/static/js/main.afb225c6.js.map
streamlit_browser_session_storage-0.0.12.dist-info/LICENSE
streamlit_browser_session_storage-0.0.12.dist-info/METADATA
streamlit_browser_session_storage-0.0.12.dist-info/WHEEL
streamlit_browser_session_storage-0.0.12.dist-info/top_level.txt
streamlit_browser_session_storage-0.0.12.dist-info/RECORD
